<?xml version="1.0" encoding="UTF-8" ?>
<!DOCTYPE mapper PUBLIC "-//mybatis.org//DTD Mapper 3.0//EN" "http://mybatis.org/dtd/mybatis-3-mapper.dtd">

<mapper namespace="com.lguplus.medialog.project.board.BoardDao">

	<!-- 리스트 출력 -->
	<select id="selectBoardList"
		resultType="com.lguplus.medialog.project.board.Board">
		/* board-mapper.xml(selectBoardList) */
		
				<![CDATA[
		SELECT
			BOARD_ID, BOARD_USER, BOARD_NM, BOARD_CONTENT, BOARD_REG_DT,
			BOARD_MOD_DT, BOARD_DEL_DT, BOARD_VIEW, BOARD_COMMENT, BOARD_LIKES
		FROM
			BOARD
		ORDER BY
			BOARD_ID DESC
				]]>
	</select>

	<!-- 글작성 -->
	<insert id="uploadBoard"
		parameterType="com.lguplus.medialog.project.board.Board" useGeneratedKeys="true" keyProperty="boardId">
		/* board-mapper.xml(uploadBoard) */
		INSERT INTO BOARD (
			BOARD_USER,
			BOARD_NM,
			BOARD_CONTENT,
			BOARD_REG_DT,
			BOARD_MOD_DT,
			BOARD_DEL_DT,
			BOARD_VIEW,
			BOARD_COMMENT,
			BOARD_LIKES
			) 
		VALUES (
				#{boardUser}, #{boardNm}, #{boardContent}, now(),
				NULL, NULL, '0', '0', '0'
		    )
	</insert>

	<!-- 상세 -->
	<select id="getBoardDetail"
		parameterType="int" resultType="com.lguplus.medialog.project.board.Board">
		/* board-mapper.xml(getBoardDetail) */
		SELECT
			BOARD_ID,
			BOARD_USER, 
			BOARD_NM, 
			BOARD_CONTENT, 
			BOARD_REG_DT,
			BOARD_MOD_DT, 
			BOARD_DEL_DT, 
			BOARD_VIEW, 
			BOARD_COMMENT, 
			BOARD_LIKES
		FROM
			BOARD
		WHERE
			BOARD_ID = #{id}
	</select>

	<!-- 수정 -->
	<update id="boardModifyRegist"
		parameterType="com.lguplus.medialog.project.board.Board">
		update board
			SET BOARD_NM = #{boardNm},
				BOARD_CONTENT  = #{boardContent},
				BOARD_MOD_DT = now() 
			WHERE BOARD_ID = #{boardId};		
	</update>

	<!-- 삭제 -->
	<delete id="boardDelete" parameterType="int">
        DELETE FROM board
        WHERE BOARD_ID = #{id}
    </delete>

	<!-- 조회수 -->
	<update id="boardViewUpdate">
		update board
			set BOARD_VIEW = BOARD_VIEW + 1
			where BOARD_ID = #{id}
	</update>

	<!-- 글작성 -->
	<insert id="commentPost"
		parameterType="com.lguplus.medialog.project.board.BoardComment">
		/* board-mapper.xml(uploadBoard) */
		INSERT INTO COMMENT (
			COMMENT_UPPER,
			COMMENT_PARENT,
			COMMENT_DEPTH,
			COMMENT_ORDER,
			COMMENT_USER,
			COMMENT_CONTENT,
			COMMENT_REG_DT,
			COMMENT_MOD_DT,
			COMMENT_DEL_DT
			) 
		VALUES (
				#{commentUpper}, 0, 0, 0, #{commentUser}, #{commentContent}, now(), 
				NULL, NULL
		    )
	</insert>
	
	<!-- 댓글 리스트 출력 -->
	<select id="openCommentList"
		resultType="com.lguplus.medialog.project.board.BoardComment">
		/* board-mapper.xml(openCommentList) */
		
				<![CDATA[
		SELECT
			COMMENT_ID,
			COMMENT_UPPER,
			COMMENT_PARENT,
			COMMENT_DEPTH,
			COMMENT_ORDER,
			COMMENT_USER,
			COMMENT_CONTENT,
			COMMENT_REG_DT,
			COMMENT_MOD_DT,
			COMMENT_DEL_DT
		FROM
			comment
		WHERE
			COMMENT_UPPER = #{commentUpper}
		ORDER BY
			COMMENT_ID
			
				]]>
	
	</select>
	<!-- 댓글 수 추가-->
	<update id="addCommentCnt">
		update
			board
		set
			BOARD_COMMENT = BOARD_COMMENT+ 1
		where
			BOARD_ID = #{boardId}
	
	</update>
	<!-- 댓글 수 빼기-->
	<update id="subCommentCnt">
		update
			board
		set
			BOARD_COMMENT = BOARD_COMMENT- 1
		where
			BOARD_ID = #{boardId}
	
	</update>
	
	<!-- 댓삭제 -->
	<delete id="commentDelete" parameterType="int">
        DELETE FROM comment
        WHERE COMMENT_ID = #{id}
    </delete>
	


	<!-- <update id="increaseFailCount" parameterType="string"> /* authuser-mapper.xml(increaseFailCount) 
		*/ UPDATE USER SET LOGIN_FAIL_CNT = IFNULL(LOGIN_FAIL_CNT, 0) + 1 WHERE USER_ID 
		= #{userId} </update> / -->

</mapper>